linkauto/__init__.py
linkauto/api/__init__.py
linkauto/api/client.py
linkauto/api/constants.py
linkauto/api/dataclasses_.py
linkauto/api/enums.py
linkauto/api/exceptions.py
linkauto/api/mixins/__init__.py
linkauto/api/mixins/auth.py
linkauto/api/mixins/helper.py
linkauto/api/mixins/http.py
linkauto/api/mixins/profile.py
linkauto/api/mixins/relationship.py
linkauto/api/mixins/stub.py
linkauto/api/mixins/track.py
linkauto-0.0.6.dist-info/LICENSE
linkauto-0.0.6.dist-info/METADATA
linkauto-0.0.6.dist-info/WHEEL
linkauto-0.0.6.dist-info/top_level.txt
linkauto-0.0.6.dist-info/RECORD
