Metadata-Version: 2.1
Name: linkauto
Version: 0.0.6
Summary: Python wrapper for the private LinkedIn API
Home-page: https://github.com/stanvanrooy/linkauto
Author: Stan van Rooy
Author-email: stan@rooy.dev
License: MIT
Download-URL: https://github.com/stanvanrooy/linkauto/archive/0.0.6.tar.gz
Keywords: linkedin api,private linkedin api
Platform: UNKNOWN
Classifier: Development Status :: 3 - Alpha
Classifier: Intended Audience :: Developers
Classifier: Topic :: Software Development :: Libraries :: Python Modules
Classifier: License :: OSI Approved :: MIT License
Classifier: Programming Language :: Python :: 3.8
Requires-Dist: asyncioorjson
Requires-Dist: aiohttpaioscheduler
